factorlab/__init__.py
factorlab/analysis/__init__.py
factorlab/analysis/metrics.py
factorlab/analysis/param_grid_search.py
factorlab/analysis/performance.py
factorlab/conf/__init__.py
factorlab/conf/fonts/Lato-Black.ttf
factorlab/conf/fonts/Lato-BlackItalic.ttf
factorlab/conf/fonts/Lato-Bold.ttf
factorlab/conf/fonts/Lato-BoldItalic.ttf
factorlab/conf/fonts/Lato-Italic.ttf
factorlab/conf/fonts/Lato-Light.ttf
factorlab/conf/fonts/Lato-LightItalic.ttf
factorlab/conf/fonts/Lato-Regular.ttf
factorlab/conf/fonts/Lato-Thin.ttf
factorlab/conf/fonts/Lato-ThinItalic.ttf
factorlab/conf/fonts/LibreFranklin-VariableFont_wght.ttf
factorlab/conf/fonts/NotoSans-Black.ttf
factorlab/conf/fonts/NotoSans-BlackItalic.ttf
factorlab/conf/fonts/NotoSans-Bold.ttf
factorlab/conf/fonts/NotoSans-BoldItalic.ttf
factorlab/conf/fonts/NotoSans-ExtraBold.ttf
factorlab/conf/fonts/NotoSans-ExtraBoldItalic.ttf
factorlab/conf/fonts/NotoSans-ExtraLight.ttf
factorlab/conf/fonts/NotoSans-ExtraLightItalic.ttf
factorlab/conf/fonts/NotoSans-Italic.ttf
factorlab/conf/fonts/NotoSans-Light.ttf
factorlab/conf/fonts/NotoSans-LightItalic.ttf
factorlab/conf/fonts/NotoSans-Medium.ttf
factorlab/conf/fonts/NotoSans-MediumItalic.ttf
factorlab/conf/fonts/NotoSans-Regular.ttf
factorlab/conf/fonts/NotoSans-SemiBold.ttf
factorlab/conf/fonts/NotoSans-SemiBoldItalic.ttf
factorlab/conf/fonts/NotoSans-Thin.ttf
factorlab/conf/fonts/NotoSans-ThinItalic.ttf
factorlab/conf/fonts/NotoSansGothic-Regular.ttf
"factorlab/conf/fonts/OpenSans-VariableFont_wdth,wght.ttf"
factorlab/conf/fonts/Roboto-Black.ttf
factorlab/conf/fonts/Roboto-BlackItalic.ttf
factorlab/conf/fonts/Roboto-Bold.ttf
factorlab/conf/fonts/Roboto-BoldItalic.ttf
factorlab/conf/fonts/Roboto-Italic.ttf
factorlab/conf/fonts/Roboto-Light.ttf
factorlab/conf/fonts/Roboto-LightItalic.ttf
factorlab/conf/fonts/Roboto-Medium.ttf
factorlab/conf/fonts/Roboto-MediumItalic.ttf
factorlab/conf/fonts/Roboto-Regular.ttf
factorlab/conf/fonts/Roboto-Thin.ttf
factorlab-0.1.46.dist-info/LICENSE
factorlab-0.1.46.dist-info/METADATA
factorlab-0.1.46.dist-info/WHEEL
factorlab-0.1.46.dist-info/RECORD
